byzerllm/__init__.py
byzerllm/byzerllm.py
byzerllm/byzerllm_command.py
byzerllm/command_args.py
byzerllm/easy_byzerllm_command.py
byzerllm/lang.py
byzerllm/log.py
byzerllm/store.py
byzerllm/types.py
byzerllm/version.py
byzerllm/alpha_moss/__init__.py
byzerllm/apps/__init__.py
byzerllm/apps/builder.py
byzerllm/apps/client.py
byzerllm/apps/command.py
byzerllm/apps/qa.py
byzerllm/apps/qa_strategy.py
byzerllm/apps/utils.py
byzerllm/apps/vector_db.py
byzerllm/apps/agent/__init__.py
byzerllm/apps/agent/agent.py
byzerllm/apps/agent/conversable_agent.py
byzerllm/apps/agent/groupchat.py
byzerllm/apps/agent/registry.py
byzerllm/apps/agent/user_proxy_agent.py
byzerllm/apps/agent/extensions/__init__.py
byzerllm/apps/agent/extensions/assistant_agent.py
byzerllm/apps/agent/extensions/byzer_engine_agent.py
byzerllm/apps/agent/extensions/common_agent.py
byzerllm/apps/agent/extensions/data_analysis.py
byzerllm/apps/agent/extensions/data_analysis_pipeline_agent.py
byzerllm/apps/agent/extensions/llama_index_retrieval_agent.py
byzerllm/apps/agent/extensions/load_data_agent.py
byzerllm/apps/agent/extensions/output_agent.py
byzerllm/apps/agent/extensions/planner.py
byzerllm/apps/agent/extensions/preview_file_agent.py
byzerllm/apps/agent/extensions/python_codesandbox_agent.py
byzerllm/apps/agent/extensions/retrieval_agent.py
byzerllm/apps/agent/extensions/rhetorical_agent.py
byzerllm/apps/agent/extensions/simple_retrieval_client.py
byzerllm/apps/agent/extensions/spark_sql_agent.py
byzerllm/apps/agent/extensions/sql_reviewer_agent.py
byzerllm/apps/agent/extensions/subquestion_agent.py
byzerllm/apps/agent/extensions/visualization_agent.py
byzerllm/apps/agent/extensions/query_rewrite/__init__.py
byzerllm/apps/agent/extensions/query_rewrite/condition.py
byzerllm/apps/agent/extensions/query_rewrite/context.py
byzerllm/apps/agent/extensions/query_rewrite/rhetorical.py
byzerllm/apps/agent/extensions/query_rewrite/time.py
byzerllm/apps/agent/store/__init__.py
byzerllm-0.1.200.dist-info/LICENSE
byzerllm-0.1.200.dist-info/METADATA
byzerllm-0.1.200.dist-info/WHEEL
byzerllm-0.1.200.dist-info/entry_points.txt
byzerllm-0.1.200.dist-info/top_level.txt
byzerllm-0.1.200.dist-info/RECORD
