Metadata-Version: 2.1
Name: byzerllm
Version: 0.1.200
Summary: ByzerLLM: Byzer LLM
Author: allwefantasy
Classifier: Topic :: Scientific/Engineering :: Artificial Intelligence
Classifier: Programming Language :: Python :: 3.9
Classifier: Programming Language :: Python :: 3.10
Classifier: Programming Language :: Python :: 3.11
License-File: LICENSE
Requires-Dist: contextlib2
Requires-Dist: ninja
Requires-Dist: jinja2
Requires-Dist: rich
Requires-Dist: ray[default] ==2.47.1
Requires-Dist: pyarrow
Requires-Dist: datasets
Requires-Dist: langchain ==0.2.7
Requires-Dist: paramiko
Requires-Dist: einops
Requires-Dist: tqdm
Requires-Dist: loguru
Requires-Dist: pyjava >=0.6.21
Requires-Dist: tiktoken
Requires-Dist: fastapi
Requires-Dist: uvicorn
Requires-Dist: retrying
Requires-Dist: zhipuai
Requires-Dist: dashscope
Requires-Dist: tabulate
Requires-Dist: jupyter-client
Requires-Dist: prompt-toolkit
Requires-Dist: websocket-client
Requires-Dist: sqlmodel
Requires-Dist: jieba
Requires-Dist: json5
Requires-Dist: modelscope
Requires-Dist: huggingface-hub
Requires-Dist: wudao
Requires-Dist: openai >=1.59.8
Requires-Dist: anthropic
Requires-Dist: google-generativeai
Requires-Dist: protobuf
Requires-Dist: azure-cognitiveservices-speech
Provides-Extra: default
Requires-Dist: contextlib2 ; extra == 'default'
Requires-Dist: ninja ; extra == 'default'
Requires-Dist: jinja2 ; extra == 'default'
Requires-Dist: rich ; extra == 'default'
Requires-Dist: ray[default] ==2.47.1 ; extra == 'default'
Requires-Dist: pyarrow ; extra == 'default'
Requires-Dist: datasets ; extra == 'default'
Requires-Dist: langchain ==0.2.7 ; extra == 'default'
Requires-Dist: paramiko ; extra == 'default'
Requires-Dist: einops ; extra == 'default'
Requires-Dist: tqdm ; extra == 'default'
Requires-Dist: loguru ; extra == 'default'
Requires-Dist: pyjava >=0.6.21 ; extra == 'default'
Requires-Dist: tiktoken ; extra == 'default'
Requires-Dist: fastapi ; extra == 'default'
Requires-Dist: uvicorn ; extra == 'default'
Requires-Dist: retrying ; extra == 'default'
Requires-Dist: zhipuai ; extra == 'default'
Requires-Dist: dashscope ; extra == 'default'
Requires-Dist: tabulate ; extra == 'default'
Requires-Dist: jupyter-client ; extra == 'default'
Requires-Dist: prompt-toolkit ; extra == 'default'
Requires-Dist: websocket-client ; extra == 'default'
Requires-Dist: sqlmodel ; extra == 'default'
Requires-Dist: jieba ; extra == 'default'
Requires-Dist: json5 ; extra == 'default'
Requires-Dist: modelscope ; extra == 'default'
Requires-Dist: huggingface-hub ; extra == 'default'
Requires-Dist: wudao ; extra == 'default'
Requires-Dist: openai >=1.59.8 ; extra == 'default'
Requires-Dist: anthropic ; extra == 'default'
Requires-Dist: google-generativeai ; extra == 'default'
Requires-Dist: protobuf ; extra == 'default'
Requires-Dist: azure-cognitiveservices-speech ; extra == 'default'
Requires-Dist: accelerate ; extra == 'default'
Requires-Dist: bitsandbytes >=0.39.0 ; extra == 'default'
Requires-Dist: transformers >=4.35.0 ; extra == 'default'
Requires-Dist: torch >=2.1.2 ; extra == 'default'
Requires-Dist: sentence-transformers ; extra == 'default'
Requires-Dist: transformers-stream-generator ; extra == 'default'
Requires-Dist: optimum ; extra == 'default'
Requires-Dist: sentencepiece ; extra == 'default'
Provides-Extra: local
Requires-Dist: contextlib2 ; extra == 'local'
Requires-Dist: ninja ; extra == 'local'
Requires-Dist: jinja2 ; extra == 'local'
Requires-Dist: rich ; extra == 'local'
Requires-Dist: ray[default] ==2.47.1 ; extra == 'local'
Requires-Dist: pyarrow ; extra == 'local'
Requires-Dist: datasets ; extra == 'local'
Requires-Dist: langchain ==0.2.7 ; extra == 'local'
Requires-Dist: paramiko ; extra == 'local'
Requires-Dist: einops ; extra == 'local'
Requires-Dist: tqdm ; extra == 'local'
Requires-Dist: loguru ; extra == 'local'
Requires-Dist: pyjava >=0.6.21 ; extra == 'local'
Requires-Dist: tiktoken ; extra == 'local'
Requires-Dist: fastapi ; extra == 'local'
Requires-Dist: uvicorn ; extra == 'local'
Requires-Dist: retrying ; extra == 'local'
Requires-Dist: zhipuai ; extra == 'local'
Requires-Dist: dashscope ; extra == 'local'
Requires-Dist: tabulate ; extra == 'local'
Requires-Dist: jupyter-client ; extra == 'local'
Requires-Dist: prompt-toolkit ; extra == 'local'
Requires-Dist: websocket-client ; extra == 'local'
Requires-Dist: sqlmodel ; extra == 'local'
Requires-Dist: jieba ; extra == 'local'
Requires-Dist: json5 ; extra == 'local'
Requires-Dist: modelscope ; extra == 'local'
Requires-Dist: huggingface-hub ; extra == 'local'
Requires-Dist: wudao ; extra == 'local'
Requires-Dist: openai >=1.59.8 ; extra == 'local'
Requires-Dist: anthropic ; extra == 'local'
Requires-Dist: google-generativeai ; extra == 'local'
Requires-Dist: protobuf ; extra == 'local'
Requires-Dist: azure-cognitiveservices-speech ; extra == 'local'
Requires-Dist: accelerate ; extra == 'local'
Requires-Dist: bitsandbytes >=0.39.0 ; extra == 'local'
Requires-Dist: transformers >=4.35.0 ; extra == 'local'
Requires-Dist: torch >=2.1.2 ; extra == 'local'
Requires-Dist: sentence-transformers ; extra == 'local'
Requires-Dist: transformers-stream-generator ; extra == 'local'
Requires-Dist: optimum ; extra == 'local'
Requires-Dist: sentencepiece ; extra == 'local'
Provides-Extra: saas
Requires-Dist: contextlib2 ; extra == 'saas'
Requires-Dist: ninja ; extra == 'saas'
Requires-Dist: jinja2 ; extra == 'saas'
Requires-Dist: rich ; extra == 'saas'
Requires-Dist: ray[default] ==2.47.1 ; extra == 'saas'
Requires-Dist: pyarrow ; extra == 'saas'
Requires-Dist: datasets ; extra == 'saas'
Requires-Dist: langchain ==0.2.7 ; extra == 'saas'
Requires-Dist: paramiko ; extra == 'saas'
Requires-Dist: einops ; extra == 'saas'
Requires-Dist: tqdm ; extra == 'saas'
Requires-Dist: loguru ; extra == 'saas'
Requires-Dist: pyjava >=0.6.21 ; extra == 'saas'
Requires-Dist: tiktoken ; extra == 'saas'
Requires-Dist: fastapi ; extra == 'saas'
Requires-Dist: uvicorn ; extra == 'saas'
Requires-Dist: retrying ; extra == 'saas'
Requires-Dist: zhipuai ; extra == 'saas'
Requires-Dist: dashscope ; extra == 'saas'
Requires-Dist: tabulate ; extra == 'saas'
Requires-Dist: jupyter-client ; extra == 'saas'
Requires-Dist: prompt-toolkit ; extra == 'saas'
Requires-Dist: websocket-client ; extra == 'saas'
Requires-Dist: sqlmodel ; extra == 'saas'
Requires-Dist: jieba ; extra == 'saas'
Requires-Dist: json5 ; extra == 'saas'
Requires-Dist: modelscope ; extra == 'saas'
Requires-Dist: huggingface-hub ; extra == 'saas'
Requires-Dist: wudao ; extra == 'saas'
Requires-Dist: openai >=1.59.8 ; extra == 'saas'
Requires-Dist: anthropic ; extra == 'saas'
Requires-Dist: google-generativeai ; extra == 'saas'
Requires-Dist: protobuf ; extra == 'saas'
Requires-Dist: azure-cognitiveservices-speech ; extra == 'saas'
